simple_revert/__init__.py
simple_revert/common.py
simple_revert/restore_version.py
simple_revert/simple_revert.py
simple_revert-1.2.0.dist-info/LICENSE.md
simple_revert-1.2.0.dist-info/METADATA
simple_revert-1.2.0.dist-info/WHEEL
simple_revert-1.2.0.dist-info/entry_points.txt
simple_revert-1.2.0.dist-info/top_level.txt
simple_revert-1.2.0.dist-info/RECORD
