Metadata-Version: 2.1
Name: simple_revert
Version: 1.2.0
Summary: CLI tool and library to revert changes in OpenStreetMap
Home-page: https://github.com/Zverik/simple-revert
Author: Ilya Zverev
Author-email: ilya@zverev.info
Classifier: Development Status :: 4 - Beta
Classifier: Environment :: Console
Classifier: Intended Audience :: Information Technology
Classifier: Intended Audience :: Customer Service
Classifier: Operating System :: OS Independent
Classifier: License :: OSI Approved :: ISC License (ISCL)
Classifier: Programming Language :: Python :: 2.7
Classifier: Programming Language :: Python :: 3
Requires-Python: !=3.0.*,!=3.1.*,!=3.2.*,>=2.7
License-File: LICENSE.md
Requires-Dist: requests
Requires-Dist: cli-oauth2
